dewloosh/solid/__init__.py
dewloosh/solid/config.py
dewloosh/solid/fem/__init__.py
dewloosh/solid/fem/config.py
dewloosh/solid/fem/dyn.py
dewloosh/solid/fem/eigsolve.py
dewloosh/solid/fem/elem.py
dewloosh/solid/fem/femsolver.py
dewloosh/solid/fem/imap.py
dewloosh/solid/fem/linsolve.py
dewloosh/solid/fem/mesh.py
dewloosh/solid/fem/mesh2d.py
dewloosh/solid/fem/meta.py
dewloosh/solid/fem/pointdata.py
dewloosh/solid/fem/postproc.py
dewloosh/solid/fem/preproc.py
dewloosh/solid/fem/utils.py
dewloosh/solid/fem/cells/__init__.py
dewloosh/solid/fem/cells/bernoulli.py
dewloosh/solid/fem/cells/bernoulli2.py
dewloosh/solid/fem/cells/bernoulli3.py
dewloosh/solid/fem/cells/cst.py
dewloosh/solid/fem/cells/felippa.py
dewloosh/solid/fem/cells/h27.py
dewloosh/solid/fem/cells/h8.py
dewloosh/solid/fem/cells/lst.py
dewloosh/solid/fem/cells/q4.py
dewloosh/solid/fem/cells/q9.py
dewloosh/solid/fem/cells/tet10.py
dewloosh/solid/fem/cells/tet4.py
dewloosh/solid/fem/cells/turner.py
dewloosh/solid/fem/cells/gen/b2.py
dewloosh/solid/fem/cells/gen/b3.py
dewloosh/solid/fem/cells/utils/__init__.py
dewloosh/solid/fem/cells/utils/bernoulli.py
dewloosh/solid/fem/cells/utils/utils.py
dewloosh/solid/fem/model/beam.py
dewloosh/solid/fem/model/membrane.py
dewloosh/solid/fem/model/plate.py
dewloosh/solid/fem/model/solid.py
dewloosh/solid/fem/model/solid3d.py
dewloosh/solid/fem/model/surface.py
dewloosh/solid/fem/model/utils.py
dewloosh/solid/fem/structure/__init__.py
dewloosh/solid/fem/structure/domain.py
dewloosh/solid/fem/structure/linemesh.py
dewloosh/solid/fem/structure/structure.py
dewloosh/solid/fem/structure/tr.py
dewloosh/solid/fourier/__init__.py
dewloosh/solid/fourier/beam.py
dewloosh/solid/fourier/doc.py
dewloosh/solid/fourier/latex.py
dewloosh/solid/fourier/loads.py
dewloosh/solid/fourier/plate.py
dewloosh/solid/fourier/plot.py
dewloosh/solid/fourier/postproc.py
dewloosh/solid/fourier/preproc.py
dewloosh/solid/fourier/proc.py
dewloosh/solid/fourier/symtools.py
dewloosh.solid-0.0.1a7.dist-info/LICENSE
dewloosh.solid-0.0.1a7.dist-info/METADATA
dewloosh.solid-0.0.1a7.dist-info/WHEEL
dewloosh.solid-0.0.1a7.dist-info/top_level.txt
dewloosh.solid-0.0.1a7.dist-info/RECORD
