Metadata-Version: 2.1
Name: dewloosh.solid
Version: 0.0.1a7
Summary: A package to build and manage polygonal data
Home-page: UNKNOWN
Author: dewloosh
Author-email: dewloosh@gmail.com
License: UNKNOWN
Platform: UNKNOWN
Classifier: Development Status :: 3 - Alpha
Classifier: License :: OSI Approved :: MIT License
Classifier: Programming Language :: Python :: 3
Classifier: Operating System :: OS Independent
Requires-Python: >=3.6
Requires-Dist: dewloosh.geom
